<annotation>
   <folder>chromosome_original</folder>
   <filename>103095.jpg</filename>
   <path>D:\Taichung_chromosomes\chromosome_original\103095.jpg</path>
   <source>
      <database>Unknow</database>
   </source>
   <size>
      <width>756</width>
      <height>872</height>
      <depth>3</depth>
   </size>
   <segmented>0</segmented>
   <object>
      <name>A1</name>
      <pose>Unspecified</pose>
      <truncated>0</truncated>
      <difficult>0</difficult>
      <bndbox>
         <xmin>588</xmin>
         <ymin>177</ymin>
         <xmax>673</xmax>
         <ymax>289</ymax>
      </bndbox>
   </object>
   <object>
      <name>A1</name>
      <pose>Unspecified</pose>
      <truncated>0</truncated>
      <difficult>0</difficult>
      <bndbox>
         <xmin>285</xmin>
         <ymin>138</ymin>
         <xmax>395</xmax>
         <ymax>219</ymax>
      </bndbox>
   </object>
   <object>
      <name>A2</name>
      <pose>Unspecified</pose>
      <truncated>0</truncated>
      <difficult>0</difficult>
      <bndbox>
         <xmin>344</xmin>
         <ymin>422</ymin>
         <xmax>431</xmax>
         <ymax>510</ymax>
      </bndbox>
   </object>
   <object>
      <name>A2</name>
      <pose>Unspecified</pose>
      <truncated>0</truncated>
      <difficult>0</difficult>
      <bndbox>
         <xmin>643</xmin>
         <ymin>333</ymin>
         <xmax>723</xmax>
         <ymax>439</ymax>
      </bndbox>
   </object>
   <object>
      <name>A3</name>
      <pose>Unspecified</pose>
      <truncated>0</truncated>
      <difficult>0</difficult>
      <bndbox>
         <xmin>206</xmin>
         <ymin>600</ymin>
         <xmax>243</xmax>
         <ymax>701</ymax>
      </bndbox>
   </object>
   <object>
      <name>A3</name>
      <pose>Unspecified</pose>
      <truncated>0</truncated>
      <difficult>0</difficult>
      <bndbox>
         <xmin>340</xmin>
         <ymin>366</ymin>
         <xmax>438</xmax>
         <ymax>407</ymax>
      </bndbox>
   </object>
   <object>
      <name>B4</name>
      <pose>Unspecified</pose>
      <truncated>0</truncated>
      <difficult>0</difficult>
      <bndbox>
         <xmin>464</xmin>
         <ymin>657</ymin>
         <xmax>556</xmax>
         <ymax>691</ymax>
      </bndbox>
   </object>
   <object>
      <name>B4</name>
      <pose>Unspecified</pose>
      <truncated>0</truncated>
      <difficult>0</difficult>
      <bndbox>
         <xmin>226</xmin>
         <ymin>582</ymin>
         <xmax>272</xmax>
         <ymax>676</ymax>
      </bndbox>
   </object>
   <object>
      <name>B5</name>
      <pose>Unspecified</pose>
      <truncated>0</truncated>
      <difficult>0</difficult>
      <bndbox>
         <xmin>229</xmin>
         <ymin>176</ymin>
         <xmax>314</xmax>
         <ymax>217</ymax>
      </bndbox>
   </object>
   <object>
      <name>B5</name>
      <pose>Unspecified</pose>
      <truncated>0</truncated>
      <difficult>0</difficult>
      <bndbox>
         <xmin>144</xmin>
         <ymin>279</ymin>
         <xmax>189</xmax>
         <ymax>372</ymax>
      </bndbox>
   </object>
   <object>
      <name>C6</name>
      <pose>Unspecified</pose>
      <truncated>0</truncated>
      <difficult>0</difficult>
      <bndbox>
         <xmin>560</xmin>
         <ymin>89</ymin>
         <xmax>589</xmax>
         <ymax>188</ymax>
      </bndbox>
   </object>
   <object>
      <name>C6</name>
      <pose>Unspecified</pose>
      <truncated>0</truncated>
      <difficult>0</difficult>
      <bndbox>
         <xmin>597</xmin>
         <ymin>444</ymin>
         <xmax>695</xmax>
         <ymax>488</ymax>
      </bndbox>
   </object>
   <object>
      <name>C7</name>
      <pose>Unspecified</pose>
      <truncated>0</truncated>
      <difficult>0</difficult>
      <bndbox>
         <xmin>292</xmin>
         <ymin>397</ymin>
         <xmax>343</xmax>
         <ymax>471</ymax>
      </bndbox>
   </object>
   <object>
      <name>C7</name>
      <pose>Unspecified</pose>
      <truncated>0</truncated>
      <difficult>0</difficult>
      <bndbox>
         <xmin>518</xmin>
         <ymin>501</ymin>
         <xmax>563</xmax>
         <ymax>584</ymax>
      </bndbox>
   </object>
   <object>
      <name>C8</name>
      <pose>Unspecified</pose>
      <truncated>0</truncated>
      <difficult>0</difficult>
      <bndbox>
         <xmin>444</xmin>
         <ymin>28</ymin>
         <xmax>522</xmax>
         <ymax>85</ymax>
      </bndbox>
   </object>
   <object>
      <name>C8</name>
      <pose>Unspecified</pose>
      <truncated>0</truncated>
      <difficult>0</difficult>
      <bndbox>
         <xmin>295</xmin>
         <ymin>683</ymin>
         <xmax>366</xmax>
         <ymax>744</ymax>
      </bndbox>
   </object>
   <object>
      <name>C9</name>
      <pose>Unspecified</pose>
      <truncated>0</truncated>
      <difficult>0</difficult>
      <bndbox>
         <xmin>227</xmin>
         <ymin>268</ymin>
         <xmax>298</xmax>
         <ymax>316</ymax>
      </bndbox>
   </object>
   <object>
      <name>C9</name>
      <pose>Unspecified</pose>
      <truncated>0</truncated>
      <difficult>0</difficult>
      <bndbox>
         <xmin>133</xmin>
         <ymin>456</ymin>
         <xmax>183</xmax>
         <ymax>537</ymax>
      </bndbox>
   </object>
   <object>
      <name>C10</name>
      <pose>Unspecified</pose>
      <truncated>0</truncated>
      <difficult>0</difficult>
      <bndbox>
         <xmin>422</xmin>
         <ymin>186</ymin>
         <xmax>463</xmax>
         <ymax>260</ymax>
      </bndbox>
   </object>
   <object>
      <name>C10</name>
      <pose>Unspecified</pose>
      <truncated>0</truncated>
      <difficult>0</difficult>
      <bndbox>
         <xmin>419</xmin>
         <ymin>629</ymin>
         <xmax>485</xmax>
         <ymax>688</ymax>
      </bndbox>
   </object>
   <object>
      <name>C11</name>
      <pose>Unspecified</pose>
      <truncated>0</truncated>
      <difficult>0</difficult>
      <bndbox>
         <xmin>143</xmin>
         <ymin>548</ymin>
         <xmax>197</xmax>
         <ymax>624</ymax>
      </bndbox>
   </object>
   <object>
      <name>C11</name>
      <pose>Unspecified</pose>
      <truncated>0</truncated>
      <difficult>0</difficult>
      <bndbox>
         <xmin>536</xmin>
         <ymin>462</ymin>
         <xmax>599</xmax>
         <ymax>528</ymax>
      </bndbox>
   </object>
   <object>
      <name>C12</name>
      <pose>Unspecified</pose>
      <truncated>0</truncated>
      <difficult>0</difficult>
      <bndbox>
         <xmin>374</xmin>
         <ymin>733</ymin>
         <xmax>432</xmax>
         <ymax>809</ymax>
      </bndbox>
   </object>
   <object>
      <name>C12</name>
      <pose>Unspecified</pose>
      <truncated>0</truncated>
      <difficult>0</difficult>
      <bndbox>
         <xmin>255</xmin>
         <ymin>699</ymin>
         <xmax>329</xmax>
         <ymax>743</ymax>
      </bndbox>
   </object>
   <object>
      <name>D13</name>
      <pose>Unspecified</pose>
      <truncated>0</truncated>
      <difficult>0</difficult>
      <bndbox>
         <xmin>191</xmin>
         <ymin>197</ymin>
         <xmax>231</xmax>
         <ymax>256</ymax>
      </bndbox>
   </object>
   <object>
      <name>D13</name>
      <pose>Unspecified</pose>
      <truncated>0</truncated>
      <difficult>0</difficult>
      <bndbox>
         <xmin>552</xmin>
         <ymin>364</ymin>
         <xmax>622</xmax>
         <ymax>415</ymax>
      </bndbox>
   </object>
   <object>
      <name>D14</name>
      <pose>Unspecified</pose>
      <truncated>0</truncated>
      <difficult>0</difficult>
      <bndbox>
         <xmin>522</xmin>
         <ymin>681</ymin>
         <xmax>569</xmax>
         <ymax>731</ymax>
      </bndbox>
   </object>
   <object>
      <name>D14</name>
      <pose>Unspecified</pose>
      <truncated>0</truncated>
      <difficult>0</difficult>
      <bndbox>
         <xmin>314</xmin>
         <ymin>431</ymin>
         <xmax>374</xmax>
         <ymax>474</ymax>
      </bndbox>
   </object>
   <object>
      <name>D15</name>
      <pose>Unspecified</pose>
      <truncated>0</truncated>
      <difficult>0</difficult>
      <bndbox>
         <xmin>470</xmin>
         <ymin>522</ymin>
         <xmax>527</xmax>
         <ymax>566</ymax>
      </bndbox>
   </object>
   <object>
      <name>D15</name>
      <pose>Unspecified</pose>
      <truncated>0</truncated>
      <difficult>0</difficult>
      <bndbox>
         <xmin>180</xmin>
         <ymin>350</ymin>
         <xmax>226</xmax>
         <ymax>404</ymax>
      </bndbox>
   </object>
   <object>
      <name>E16</name>
      <pose>Unspecified</pose>
      <truncated>0</truncated>
      <difficult>0</difficult>
      <bndbox>
         <xmin>155</xmin>
         <ymin>417</ymin>
         <xmax>188</xmax>
         <ymax>471</ymax>
      </bndbox>
   </object>
   <object>
      <name>E16</name>
      <pose>Unspecified</pose>
      <truncated>0</truncated>
      <difficult>0</difficult>
      <bndbox>
         <xmin>400</xmin>
         <ymin>518</ymin>
         <xmax>430</xmax>
         <ymax>570</ymax>
      </bndbox>
   </object>
   <object>
      <name>E17</name>
      <pose>Unspecified</pose>
      <truncated>0</truncated>
      <difficult>0</difficult>
      <bndbox>
         <xmin>321</xmin>
         <ymin>781</ymin>
         <xmax>385</xmax>
         <ymax>822</ymax>
      </bndbox>
   </object>
   <object>
      <name>E17</name>
      <pose>Unspecified</pose>
      <truncated>0</truncated>
      <difficult>0</difficult>
      <bndbox>
         <xmin>368</xmin>
         <ymin>548</ymin>
         <xmax>403</xmax>
         <ymax>598</ymax>
      </bndbox>
   </object>
   <object>
      <name>E18</name>
      <pose>Unspecified</pose>
      <truncated>0</truncated>
      <difficult>0</difficult>
      <bndbox>
         <xmin>468</xmin>
         <ymin>786</ymin>
         <xmax>517</xmax>
         <ymax>840</ymax>
      </bndbox>
   </object>
   <object>
      <name>E18</name>
      <pose>Unspecified</pose>
      <truncated>0</truncated>
      <difficult>0</difficult>
      <bndbox>
         <xmin>270</xmin>
         <ymin>586</ymin>
         <xmax>326</xmax>
         <ymax>627</ymax>
      </bndbox>
   </object>
   <object>
      <name>F19</name>
      <pose>Unspecified</pose>
      <truncated>0</truncated>
      <difficult>0</difficult>
      <bndbox>
         <xmin>342</xmin>
         <ymin>95</ymin>
         <xmax>394</xmax>
         <ymax>129</ymax>
      </bndbox>
   </object>
   <object>
      <name>F19</name>
      <pose>Unspecified</pose>
      <truncated>0</truncated>
      <difficult>0</difficult>
      <bndbox>
         <xmin>284</xmin>
         <ymin>487</ymin>
         <xmax>330</xmax>
         <ymax>535</ymax>
      </bndbox>
   </object>
   <object>
      <name>F20</name>
      <pose>Unspecified</pose>
      <truncated>0</truncated>
      <difficult>0</difficult>
      <bndbox>
         <xmin>359</xmin>
         <ymin>143</ymin>
         <xmax>403</xmax>
         <ymax>168</ymax>
      </bndbox>
   </object>
   <object>
      <name>F20</name>
      <pose>Unspecified</pose>
      <truncated>0</truncated>
      <difficult>0</difficult>
      <bndbox>
         <xmin>259</xmin>
         <ymin>244</ymin>
         <xmax>304</xmax>
         <ymax>275</ymax>
      </bndbox>
   </object>
   <object>
      <name>G21</name>
      <pose>Unspecified</pose>
      <truncated>0</truncated>
      <difficult>0</difficult>
      <bndbox>
         <xmin>623</xmin>
         <ymin>269</ymin>
         <xmax>653</xmax>
         <ymax>304</ymax>
      </bndbox>
   </object>
   <object>
      <name>G21</name>
      <pose>Unspecified</pose>
      <truncated>0</truncated>
      <difficult>0</difficult>
      <bndbox>
         <xmin>126</xmin>
         <ymin>298</ymin>
         <xmax>160</xmax>
         <ymax>341</ymax>
      </bndbox>
   </object>
   <object>
      <name>G22</name>
      <pose>Unspecified</pose>
      <truncated>0</truncated>
      <difficult>0</difficult>
      <bndbox>
         <xmin>347</xmin>
         <ymin>253</ymin>
         <xmax>377</xmax>
         <ymax>295</ymax>
      </bndbox>
   </object>
   <object>
      <name>G22</name>
      <pose>Unspecified</pose>
      <truncated>0</truncated>
      <difficult>0</difficult>
      <bndbox>
         <xmin>173</xmin>
         <ymin>405</ymin>
         <xmax>216</xmax>
         <ymax>441</ymax>
      </bndbox>
   </object>
   <object>
      <name>X</name>
      <pose>Unspecified</pose>
      <truncated>0</truncated>
      <difficult>0</difficult>
      <bndbox>
         <xmin>444</xmin>
         <ymin>718</ymin>
         <xmax>529</xmax>
         <ymax>782</ymax>
      </bndbox>
   </object>
   <object>
      <name>Y</name>
      <pose>Unspecified</pose>
      <truncated>0</truncated>
      <difficult>0</difficult>
      <bndbox>
         <xmin>48</xmin>
         <ymin>681</ymin>
         <xmax>100</xmax>
         <ymax>737</ymax>
      </bndbox>
   </object>
</annotation>
